yaw.py
yaw_cli-0.1.2.dist-info/METADATA
yaw_cli-0.1.2.dist-info/WHEEL
yaw_cli-0.1.2.dist-info/entry_points.txt
yaw_cli-0.1.2.dist-info/top_level.txt
yaw_cli-0.1.2.dist-info/RECORD
